informathion/OpportunityLoss.py
informathion/__init__.py
informathion-0.2.3.dist-info/LICENSE
informathion-0.2.3.dist-info/WHEEL
informathion-0.2.3.dist-info/METADATA
informathion-0.2.3.dist-info/RECORD
